auto_ml_processor/__init__.py
auto_ml_processor/processor.py
auto_ml_processor-0.1.2.dist-info/METADATA
auto_ml_processor-0.1.2.dist-info/WHEEL
auto_ml_processor-0.1.2.dist-info/top_level.txt
auto_ml_processor-0.1.2.dist-info/RECORD
