Metadata-Version: 2.2
Name: auto-ml-processor
Version: 0.1.2
Summary: Automated machine learning preprocessing and modeling tool
Home-page: https://github.com/yourusername/auto-ml-processor
Author: Your Name
Author-email: your.email@example.com
Classifier: Programming Language :: Python :: 3
Classifier: License :: OSI Approved :: MIT License
Classifier: Operating System :: OS Independent
Requires-Python: >=3.6
Requires-Dist: pandas>=1.0.0
Requires-Dist: numpy>=1.18.0
Requires-Dist: scikit-learn>=0.22.0
Requires-Dist: xgboost>=1.0.0
Requires-Dist: joblib>=0.14.0
Requires-Dist: requests>=2.25.0
Provides-Extra: full
Requires-Dist: datasets>=2.0.0; extra == "full"
Requires-Dist: kaggle>=1.5.0; extra == "full"
Requires-Dist: opendatasets>=0.1.0; extra == "full"
Dynamic: author
Dynamic: author-email
Dynamic: classifier
Dynamic: description
Dynamic: description-content-type
Dynamic: home-page
Dynamic: provides-extra
Dynamic: requires-dist
Dynamic: requires-python
Dynamic: summary
